rppt/__init__.py
rppt-1.1.2.dist-info/METADATA
rppt-1.1.2.dist-info/WHEEL
rppt-1.1.2.dist-info/top_level.txt
rppt-1.1.2.dist-info/RECORD
