Metadata-Version: 2.1
Name: rppt
Version: 1.1.2
Summary: a library that simplifies writing code using "random" library
Home-page: https://github.com/Rand0mLit3ral/rppt-v1.1.0/tree/main
Author: Rand0mLit3ral
Author-email: randomliteral@mail.ru
Classifier: Programming Language :: Python :: 3
Classifier: License :: OSI Approved :: MIT License
Classifier: Operating System :: OS Independent
Requires-Python: >=3.6
